Metadata-Version: 2.1
Name: chat2note
Version: 0.1.3
Requires-Dist: openai
Requires-Dist: DrissionPage
Requires-Dist: python-dotenv
